{
    "merging_metrics": {
        "merge_success": 1.0,
        "merge_child_count": 0.0,
        "child_camera_counts": {
            "summary": {
                "min": null,
                "max": null,
                "median": null,
                "mean": null,
                "stddev": null
            },
            "full_data": []
        },
        "child_camera_overlap_with_parent": {
            "summary": {
                "min": null,
                "max": null,
                "median": null,
                "mean": null,
                "stddev": null
            },
            "full_data": []
        },
        "number_images_merged": 236.0,
        "number_cameras_merged": 44.0,
        "number_tracks_merged": 710.0,
        "3d_track_lengths_merged": {
            "summary": {
                "min": 3,
                "max": 30,
                "median": 4.0,
                "mean": 5.622535211267605,
                "stddev": 3.9401936458846825,
                "len": 710,
                "invalid": 0,
                "histogram": {
                    "3": 137,
                    "4": 88,
                    "5": 53,
                    "6": 41,
                    "7": 23,
                    "8": 20,
                    "9": 24,
                    "10": 12,
                    "11": 8,
                    "12": 6,
                    "13": 7,
                    "14": 5,
                    "15": 5,
                    "16": 6,
                    "17": 4,
                    "18": 0,
                    "19": 2,
                    "20": 3,
                    "21": 2,
                    "22": 0,
                    "23": 0,
                    "24": 0,
                    "25": 2,
                    "26": 0,
                    "27": 2,
                    "28": 0,
                    "29": 1
                }
            }
        },
        "reprojection_errors_merged_px": {
            "summary": {
                "min": 0.0018227044445791923,
                "max": 2.960562697438534,
                "median": 0.30492940283228054,
                "mean": 0.3636994859522131,
                "stddev": 0.27201563346687585,
                "len": 3992,
                "invalid": 0,
                "quartiles": {
                    "q0": 0.0018227044445791923,
                    "q1": 0.181067116791599,
                    "q2": 0.30492940283228054,
                    "q3": 0.4688579328828968,
                    "q4": 2.960562697438534
                }
            }
        },
        "rotation_angle_error_deg": {
            "summary": {
                "min": 0.0721055418252945,
                "max": 1.5656447410583496,
                "median": 0.30400216579437256,
                "mean": 0.39424705505371094,
                "stddev": 0.28847333788871765,
                "len": 44,
                "invalid": 0,
                "quartiles": {
                    "q0": 0.0721055418252945,
                    "q1": 0.19015312939882278,
                    "q2": 0.30400216579437256,
                    "q3": 0.48544755578041077,
                    "q4": 1.5656447410583496
                }
            }
        },
        "translation_error_distance": {
            "summary": {
                "min": 0.03164578229188919,
                "max": 0.5821175575256348,
                "median": 0.08827096223831177,
                "mean": 0.15385952591896057,
                "stddev": 0.1352248191833496,
                "len": 44,
                "invalid": 0,
                "quartiles": {
                    "q0": 0.03164578229188919,
                    "q1": 0.06171052344143391,
                    "q2": 0.08827096596360207,
                    "q3": 0.2099967636168003,
                    "q4": 0.5821175575256348
                }
            }
        },
        "relative_translation_angle_error_deg": {
            "summary": {
                "min": 0.035139549523591995,
                "max": 38.40809631347656,
                "median": 2.1020383834838867,
                "mean": 3.0719895362854004,
                "stddev": 3.6114206314086914,
                "len": 946,
                "invalid": 0,
                "quartiles": {
                    "q0": 0.035139549523591995,
                    "q1": 1.0918562412261963,
                    "q2": 2.1020383834838867,
                    "q3": 3.626881718635559,
                    "q4": 38.40809631347656
                }
            }
        },
        "translation_angle_error_deg": {
            "summary": {
                "min": 0.04841990768909454,
                "max": 5.952798366546631,
                "median": 0.8830243349075317,
                "mean": 1.222156047821045,
                "stddev": 1.0358737707138062,
                "len": 44,
                "invalid": 0,
                "quartiles": {
                    "q0": 0.04841990768909454,
                    "q1": 0.6234403252601624,
                    "q2": 0.8830243647098541,
                    "q3": 1.4555295407772064,
                    "q4": 5.952798366546631
                }
            }
        },
        "relative_rotation_angle_error_deg": {
            "summary": {
                "min": 0.03683578595519066,
                "max": 2.4211182594299316,
                "median": 0.4890364408493042,
                "mean": 0.5776805281639099,
                "stddev": 0.385214626789093,
                "len": 946,
                "invalid": 0,
                "quartiles": {
                    "q0": 0.03683578595519066,
                    "q1": 0.3158663734793663,
                    "q2": 0.4890364408493042,
                    "q3": 0.7159017026424408,
                    "q4": 2.4211182594299316
                }
            }
        },
        "pose_auc_@1.0_deg": 0.0742,
        "pose_auc_@2.5_deg": 0.2843,
        "pose_auc_@3.0_deg": 0.3407,
        "pose_auc_@5.0_deg": 0.5152,
        "pose_auc_@10.0_deg": 0.7208,
        "pose_auc_@20.0_deg": 0.8489,
        "pose_auc_constructed_only_@1.0_deg": 0.0742,
        "pose_auc_constructed_only_@2.5_deg": 0.2843,
        "pose_auc_constructed_only_@3.0_deg": 0.3407,
        "pose_auc_constructed_only_@5.0_deg": 0.5152,
        "pose_auc_constructed_only_@10.0_deg": 0.7208,
        "pose_auc_constructed_only_@20.0_deg": 0.8489,
        "focal_length_error_px": {
            "summary": {
                "min": 39.64202117919922,
                "max": 1036.6732177734375,
                "median": 236.09817504882812,
                "mean": 300.2949523925781,
                "stddev": 201.4732666015625,
                "len": 44,
                "invalid": 0,
                "quartiles": {
                    "q0": 39.64202117919922,
                    "q1": 152.2257957458496,
                    "q2": 236.09817504882812,
                    "q3": 462.0444107055664,
                    "q4": 1036.6732177734375
                }
            },
            "full_data": [
                487.1018981933594,
                39.64202117919922,
                170.63565063476562,
                511.7447814941406,
                397.23199462890625,
                611.1818237304688,
                167.36737060546875,
                306.01605224609375,
                83.33396911621094,
                234.64585876464844,
                237.5504913330078,
                119.68183135986328,
                196.14678955078125,
                219.64918518066406,
                125.71826934814453,
                1036.6732177734375,
                340.917236328125,
                289.5497741699219,
                482.02789306640625,
                214.435546875,
                460.8946533203125,
                65.18141174316406,
                273.2479553222656,
                144.1570587158203,
                143.7750701904297,
                552.2138671875,
                40.46211242675781,
                192.04833984375,
                260.2953796386719,
                163.42236328125,
                473.0650634765625,
                465.4936828613281,
                418.4356384277344,
                548.19580078125,
                85.70955657958984,
                431.9947204589844,
                568.36767578125,
                188.0240478515625,
                171.51194763183594,
                101.33255767822266,
                154.91537475585938,
                555.03955078125,
                76.73323059082031,
                407.2100830078125
            ]
        },
        "focal_length_error_pct": {
            "summary": {
                "min": 3.2260758876800537,
                "max": 84.20022583007812,
                "median": 19.179676055908203,
                "mean": 24.250720977783203,
                "stddev": 16.289724349975586,
                "len": 44,
                "invalid": 0,
                "quartiles": {
                    "q0": 3.2260758876800537,
                    "q1": 12.372602939605713,
                    "q2": 19.179675102233887,
                    "q3": 36.5287446975708,
                    "q4": 84.20022583007812
                }
            },
            "full_data": [
                38.3303337097168,
                3.2260758876800537,
                13.646485328674316,
                42.85969924926758,
                32.2010383605957,
                50.22861862182617,
                13.620390892028809,
                24.71059799194336,
                6.815011978149414,
                18.6226863861084,
                19.736663818359375,
                9.730230331420898,
                15.915838241577148,
                17.980451583862305,
                10.24098014831543,
                84.20022583007812,
                27.90743637084961,
                23.586654663085938,
                38.002830505371094,
                17.416791915893555,
                37.10906982421875,
                5.351511478424072,
                22.150449752807617,
                11.742999076843262,
                11.63228702545166,
                45.33775329589844,
                3.245276689529419,
                15.644210815429688,
                20.836965560913086,
                13.183475494384766,
                36.94666290283203,
                36.38943862915039,
                32.649471282958984,
                44.61228942871094,
                6.975061893463135,
                34.91712951660156,
                45.237796783447266,
                15.301436424255371,
                13.957677841186523,
                8.230389595031738,
                12.582470893859863,
                45.56974792480469,
                6.1308112144470215,
                32.318260192871094
            ]
        },
        "k1_error": {
            "summary": {
                "min": 0.00027789216255769134,
                "max": 0.042223237454891205,
                "median": 0.010958300903439522,
                "mean": 0.013766538351774216,
                "stddev": 0.011387872509658337,
                "len": 44,
                "invalid": 0,
                "quartiles": {
                    "q0": 0.00027789216255769134,
                    "q1": 0.0055952927796170115,
                    "q2": 0.010958301369100809,
                    "q3": 0.018008537590503693,
                    "q4": 0.042223237454891205
                }
            },
            "full_data": [
                0.03380972892045975,
                0.008455554954707623,
                0.015765301883220673,
                0.021249808371067047,
                0.005703812465071678,
                0.0105974106118083,
                0.0034025118220597506,
                0.0004723763559013605,
                0.01117897592484951,
                0.00027789216255769134,
                0.012341761030256748,
                0.042223237454891205,
                0.03337414935231209,
                0.010491617023944855,
                0.006191766355186701,
                0.016928113996982574,
                0.0011926540173590183,
                0.0016020674956962466,
                0.011818117462098598,
                0.007136833388358355,
                0.00366891804151237,
                0.006096663884818554,
                0.014734967611730099,
                0.02737288363277912,
                0.011953621171414852,
                0.001451299525797367,
                0.0051717981696128845,
                0.015952467918395996,
                0.006850698962807655,
                0.03603618964552879,
                0.04091252386569977,
                0.026335783302783966,
                0.03314635157585144,
                0.010737626813352108,
                0.011767812073230743,
                0.016562622040510178,
                0.011277122423052788,
                0.0016488180262967944,
                0.007885118946433067,
                0.009647300466895103,
                0.0229653250426054,
                0.005269733723253012,
                0.0006978504243306816,
                0.023370524868369102
            ]
        },
        "k2_error": {
            "summary": {
                "min": 9.683944881544448e-06,
                "max": 0.05913010612130165,
                "median": 0.0038435468450188637,
                "mean": 0.009305673651397228,
                "stddev": 0.013035721145570278,
                "len": 44,
                "invalid": 0,
                "quartiles": {
                    "q0": 9.683944881544448e-06,
                    "q1": 0.0010793690744321793,
                    "q2": 0.0038435468450188637,
                    "q3": 0.009914768394082785,
                    "q4": 0.05913010612130165
                }
            },
            "full_data": [
                0.031175902113318443,
                0.009530468843877316,
                0.002431602217257023,
                0.002174859633669257,
                0.021747274324297905,
                0.0006237944471649826,
                0.00010668222967069596,
                9.683944881544448e-06,
                0.0011094643268734217,
                0.007345956284552813,
                0.002061330247670412,
                0.009054058231413364,
                0.03204577416181564,
                0.011067667044699192,
                0.0024701738730072975,
                0.0011306455126032233,
                4.24249519710429e-05,
                0.0006699244258925319,
                0.024031473323702812,
                0.0016156933270394802,
                0.00584331015124917,
                0.0005158283747732639,
                0.033249400556087494,
                0.0021962712053209543,
                0.0015823858557268977,
                6.135149305919185e-05,
                0.0003109327226411551,
                0.007599204778671265,
                0.003223438747227192,
                0.004419947974383831,
                0.013101030141115189,
                0.020503902807831764,
                0.05913010612130165,
                0.014976887963712215,
                0.005944645963609219,
                0.008696114644408226,
                0.0036014155484735966,
                0.006653619930148125,
                0.0004345290653873235,
                0.0009890833171084523,
                0.004085678141564131,
                0.000796511594671756,
                0.005270620808005333,
                0.04581855237483978
            ]
        }
    }
}