{
    "merging_metrics": {
        "merge_success": 1.0,
        "merge_child_count": 2.0,
        "child_camera_counts": {
            "summary": {
                "min": 49,
                "max": 86,
                "median": 67.5,
                "mean": 67.5,
                "stddev": 18.5,
                "len": 2,
                "invalid": 0,
                "quartiles": {
                    "q0": 49.0,
                    "q1": 58.25,
                    "q2": 67.5,
                    "q3": 76.75,
                    "q4": 86.0
                }
            },
            "full_data": [
                86,
                49
            ]
        },
        "child_camera_overlap_with_parent": {
            "summary": {
                "min": 48,
                "max": 53,
                "median": 50.5,
                "mean": 50.5,
                "stddev": 2.5,
                "len": 2,
                "invalid": 0,
                "quartiles": {
                    "q0": 48.0,
                    "q1": 49.25,
                    "q2": 50.5,
                    "q3": 51.75,
                    "q4": 53.0
                }
            },
            "full_data": [
                53,
                48
            ]
        },
        "number_images_merged": 96.0,
        "number_cameras_merged": 87.0,
        "number_tracks_merged": 18282.0,
        "3d_track_lengths_merged": {
            "summary": {
                "min": 3,
                "max": 65,
                "median": 6.0,
                "mean": 10.974948036319878,
                "stddev": 10.84554198223123,
                "len": 18282,
                "invalid": 0,
                "histogram": {
                    "3": 2136,
                    "4": 1496,
                    "5": 1055,
                    "6": 869,
                    "7": 746,
                    "8": 593,
                    "9": 547,
                    "10": 488,
                    "11": 368,
                    "12": 378,
                    "13": 346,
                    "14": 288,
                    "15": 282,
                    "16": 252,
                    "17": 239,
                    "18": 243,
                    "19": 209,
                    "20": 203,
                    "21": 162,
                    "22": 175,
                    "23": 175,
                    "24": 162,
                    "25": 157,
                    "26": 142,
                    "27": 131,
                    "28": 135,
                    "29": 106,
                    "30": 134,
                    "31": 108,
                    "32": 101,
                    "33": 93,
                    "34": 90,
                    "35": 74,
                    "36": 70,
                    "37": 64,
                    "38": 54,
                    "39": 65,
                    "40": 55,
                    "41": 59,
                    "42": 49,
                    "43": 55,
                    "44": 50,
                    "45": 38,
                    "46": 30,
                    "47": 36,
                    "48": 30,
                    "49": 27,
                    "50": 24,
                    "51": 25,
                    "52": 17,
                    "53": 21,
                    "54": 14,
                    "55": 9,
                    "56": 11,
                    "57": 10,
                    "58": 5,
                    "59": 2,
                    "60": 1,
                    "61": 1,
                    "62": 1,
                    "63": 0,
                    "64": 1
                }
            }
        },
        "reprojection_errors_merged_px": {
            "summary": {
                "min": 0.0006903099388458663,
                "max": 2.9977881804576563,
                "median": 0.35732499149895836,
                "mean": 0.46826610381696004,
                "stddev": 0.4012327413098619,
                "len": 200644,
                "invalid": 0,
                "quartiles": {
                    "q0": 0.0006903099388458663,
                    "q1": 0.20937632205045237,
                    "q2": 0.35732499149895836,
                    "q3": 0.5891176562623386,
                    "q4": 2.9977881804576563
                }
            }
        },
        "rotation_angle_error_deg": {
            "summary": {
                "min": 0.007425922434777021,
                "max": 90.03792572021484,
                "median": 0.05382045358419418,
                "mean": 1.1886688470840454,
                "stddev": 9.58401107788086,
                "len": 96,
                "invalid": 9,
                "quartiles": {
                    "q0": null,
                    "q1": null,
                    "q2": null,
                    "q3": null,
                    "q4": null
                }
            }
        },
        "translation_error_distance": {
            "summary": {
                "min": 0.0010935836471617222,
                "max": 0.46725910902023315,
                "median": 0.020850082859396935,
                "mean": 0.03820747509598732,
                "stddev": 0.06306963413953781,
                "len": 96,
                "invalid": 9,
                "quartiles": {
                    "q0": null,
                    "q1": null,
                    "q2": null,
                    "q3": null,
                    "q4": null
                }
            }
        },
        "relative_translation_angle_error_deg": {
            "summary": {
                "min": 0.0051283203065395355,
                "max": 95.92058563232422,
                "median": 0.6826991438865662,
                "mean": 3.452314615249634,
                "stddev": 11.461271286010742,
                "len": 4560,
                "invalid": 819,
                "quartiles": {
                    "q0": null,
                    "q1": null,
                    "q2": null,
                    "q3": null,
                    "q4": null
                }
            }
        },
        "translation_angle_error_deg": {
            "summary": {
                "min": 0.0063759759068489075,
                "max": 6.93752384185791,
                "median": 0.11502224951982498,
                "mean": 0.36722758412361145,
                "stddev": 0.8640901446342468,
                "len": 96,
                "invalid": 9,
                "quartiles": {
                    "q0": null,
                    "q1": null,
                    "q2": null,
                    "q3": null,
                    "q4": null
                }
            }
        },
        "relative_rotation_angle_error_deg": {
            "summary": {
                "min": 0.0037861645687371492,
                "max": 90.43766021728516,
                "median": 0.12014659494161606,
                "mean": 2.3172361850738525,
                "stddev": 13.464583396911621,
                "len": 4560,
                "invalid": 819,
                "quartiles": {
                    "q0": null,
                    "q1": null,
                    "q2": null,
                    "q3": null,
                    "q4": null
                }
            }
        },
        "pose_auc_@1.0_deg": 0.2819,
        "pose_auc_@2.5_deg": 0.4758,
        "pose_auc_@3.0_deg": 0.511,
        "pose_auc_@5.0_deg": 0.5955,
        "pose_auc_@10.0_deg": 0.6786,
        "pose_auc_@20.0_deg": 0.7325,
        "pose_auc_constructed_only_@1.0_deg": 0.3436,
        "pose_auc_constructed_only_@2.5_deg": 0.5799,
        "pose_auc_constructed_only_@3.0_deg": 0.6229,
        "pose_auc_constructed_only_@5.0_deg": 0.7258,
        "pose_auc_constructed_only_@10.0_deg": 0.8272,
        "pose_auc_constructed_only_@20.0_deg": 0.8929,
        "focal_length_error_px": {
            "summary": {
                "min": 3.5552761554718018,
                "max": 542.1942749023438,
                "median": 199.45094299316406,
                "mean": 248.14505004882812,
                "stddev": 142.34359741210938,
                "len": 87,
                "invalid": 0,
                "quartiles": {
                    "q0": 3.5552761554718018,
                    "q1": 141.22782135009766,
                    "q2": 199.45094299316406,
                    "q3": 390.5151062011719,
                    "q4": 542.1942749023438
                }
            },
            "full_data": [
                210.64637756347656,
                401.6748962402344,
                202.824951171875,
                245.68844604492188,
                485.40179443359375,
                112.68888854980469,
                437.2908630371094,
                204.69322204589844,
                141.97879028320312,
                144.49609375,
                164.52886962890625,
                447.26434326171875,
                202.82974243164062,
                542.1942749023438,
                155.40599060058594,
                103.3846664428711,
                407.7793884277344,
                401.1726379394531,
                153.9022674560547,
                469.5455322265625,
                3.5552761554718018,
                458.07781982421875,
                140.43292236328125,
                199.72703552246094,
                356.3324890136719,
                90.01539611816406,
                135.9084014892578,
                346.0342712402344,
                180.8203125,
                231.2980194091797,
                35.28699493408203,
                108.65858459472656,
                538.39501953125,
                448.9666748046875,
                124.29288482666016,
                400.5569152832031,
                152.70938110351562,
                119.01724243164062,
                440.2779541015625,
                413.99359130859375,
                444.8201599121094,
                172.52281188964844,
                115.10100555419922,
                173.5592498779297,
                173.5818634033203,
                485.8482971191406,
                349.5971984863281,
                82.03585052490234,
                336.1783142089844,
                438.26495361328125,
                74.34130859375,
                262.33453369140625,
                162.96615600585938,
                199.45094299316406,
                148.55177307128906,
                140.4768524169922,
                198.78689575195312,
                144.21380615234375,
                181.3955841064453,
                65.37551879882812,
                80.95098876953125,
                490.8656921386719,
                158.2996826171875,
                202.1525115966797,
                172.4859161376953,
                274.242431640625,
                118.9949722290039,
                231.3280792236328,
                84.02821350097656,
                338.8887939453125,
                498.8182067871094,
                468.7344970703125,
                71.42579650878906,
                363.9049377441406,
                509.5651550292969,
                186.48611450195312,
                380.4732971191406,
                232.498046875,
                439.8714904785156,
                269.1748046875,
                216.27780151367188,
                179.03399658203125,
                191.53831481933594,
                132.43832397460938,
                124.12067413330078,
                97.80596923828125,
                165.06271362304688
            ]
        },
        "focal_length_error_pct": {
            "summary": {
                "min": 0.5686622262001038,
                "max": 43.64421463012695,
                "median": 16.454530715942383,
                "mean": 20.657001495361328,
                "stddev": 11.24070930480957,
                "len": 87,
                "invalid": 0,
                "quartiles": {
                    "q0": 0.5686622262001038,
                    "q1": 11.954092502593994,
                    "q2": 16.454530715942383,
                    "q3": 31.752809524536133,
                    "q4": 43.64421463012695
                }
            },
            "full_data": [
                17.042587280273438,
                32.978233337402344,
                16.44171142578125,
                20.119056701660156,
                37.94573211669922,
                9.143856048583984,
                35.48286819458008,
                16.75615692138672,
                14.535093307495117,
                14.702491760253906,
                13.355722427368164,
                34.70393753051758,
                16.658443450927734,
                43.2371826171875,
                15.831905364990234,
                10.571029663085938,
                32.487205505371094,
                32.904579162597656,
                12.660600662231445,
                36.87916564941406,
                0.5686622262001038,
                36.14881896972656,
                11.156094551086426,
                15.746376037597656,
                29.31330108642578,
                7.289876461029053,
                11.997563362121582,
                28.10544776916504,
                14.729578971862793,
                18.54524803161621,
                2.886003255844116,
                8.938679695129395,
                43.64421463012695,
                36.93375015258789,
                10.134775161743164,
                38.949527740478516,
                12.554213523864746,
                9.66032886505127,
                35.658477783203125,
                33.82300567626953,
                36.02635192871094,
                14.1784029006958,
                11.754596710205078,
                16.46034049987793,
                28.87256622314453,
                37.90951156616211,
                28.70256233215332,
                6.52943754196167,
                27.278343200683594,
                35.23462677001953,
                6.061750411987305,
                20.78061866760254,
                13.13395881652832,
                16.173540115356445,
                12.07737922668457,
                11.36544132232666,
                16.161535263061523,
                11.910621643066406,
                14.776440620422363,
                10.619805335998535,
                6.549432277679443,
                38.051605224609375,
                12.832975387573242,
                16.454530715942383,
                13.955170631408691,
                27.80235481262207,
                9.67438793182373,
                19.14333724975586,
                6.854791164398193,
                26.97300148010254,
                40.27924728393555,
                36.677188873291016,
                5.6849565505981445,
                29.868057250976562,
                41.59036636352539,
                15.169864654541016,
                31.018413543701172,
                19.145095825195312,
                34.00366973876953,
                20.503870010375977,
                17.515209197998047,
                14.446438789367676,
                21.00200843811035,
                10.541095733642578,
                10.061663627624512,
                10.72433853149414,
                13.40665340423584
            ]
        },
        "k1_error": {
            "summary": {
                "min": 5.869346568943001e-05,
                "max": 0.25635144114494324,
                "median": 0.03233705833554268,
                "mean": 0.04853835701942444,
                "stddev": 0.048950035125017166,
                "len": 87,
                "invalid": 0,
                "quartiles": {
                    "q0": 5.869346568943001e-05,
                    "q1": 0.01818967517465353,
                    "q2": 0.03233705833554268,
                    "q3": 0.06378233805298805,
                    "q4": 0.25635144114494324
                }
            },
            "full_data": [
                0.06620378792285919,
                0.022924235090613365,
                0.019023006781935692,
                0.10142100602388382,
                0.03375397250056267,
                0.054804425686597824,
                0.03571998327970505,
                0.10023091733455658,
                0.064442478120327,
                0.052988361567258835,
                0.04993372783064842,
                0.03873911872506142,
                0.016747290268540382,
                0.1409570425748825,
                0.02689485065639019,
                0.023667318746447563,
                0.01653955690562725,
                0.00804550014436245,
                0.0033815689384937286,
                0.0011325348168611526,
                0.07809645682573318,
                0.03703595697879791,
                0.04357409104704857,
                0.03134661167860031,
                0.15498071908950806,
                0.0001697765983408317,
                0.10331500321626663,
                0.009385112673044205,
                0.07073874026536942,
                0.05465726926922798,
                0.031138597056269646,
                0.13905741274356842,
                0.04809463769197464,
                0.040118589997291565,
                0.029584737494587898,
                0.2148757427930832,
                0.03233705833554268,
                0.10734083503484726,
                0.0074861738830804825,
                0.014513744972646236,
                0.07959713041782379,
                0.04547987878322601,
                0.02916852757334709,
                0.050270091742277145,
                0.017003914341330528,
                0.017270969226956367,
                0.13858309388160706,
                0.04680277779698372,
                0.012436016462743282,
                0.04590339586138725,
                0.02988240122795105,
                0.04969184845685959,
                0.024560535326600075,
                0.02327437698841095,
                0.07211752980947495,
                0.0015644258819520473,
                0.01975153014063835,
                0.0800219401717186,
                0.06312219798564911,
                0.014326250180602074,
                0.0027079512365162373,
                0.07185706496238708,
                0.003978192340582609,
                0.04120869189500809,
                0.02817029505968094,
                0.024796482175588608,
                5.869346568943001e-05,
                0.05057597905397415,
                0.025210363790392876,
                0.008977086283266544,
                0.023663729429244995,
                0.08021886646747589,
                0.01625051535665989,
                0.024938466027379036,
                0.017796456813812256,
                0.018582893535494804,
                0.023435145616531372,
                0.07564975321292877,
                0.03714660927653313,
                0.25635144114494324,
                0.019402874633669853,
                0.03369252011179924,
                0.22961246967315674,
                0.022402290254831314,
                0.008985479362308979,
                0.004939955193549395,
                0.08599931746721268
            ]
        },
        "k2_error": {
            "summary": {
                "min": 0.0002719605981837958,
                "max": 9.5753755569458,
                "median": 0.10052438825368881,
                "mean": 0.2541070580482483,
                "stddev": 1.0174102783203125,
                "len": 87,
                "invalid": 0,
                "quartiles": {
                    "q0": 0.0002719605981837958,
                    "q1": 0.04111633077263832,
                    "q2": 0.10052438825368881,
                    "q3": 0.18566874414682388,
                    "q4": 9.5753755569458
                }
            },
            "full_data": [
                0.23064932227134705,
                0.050641048699617386,
                0.0008989454945549369,
                0.30999451875686646,
                0.06670019030570984,
                0.20679813623428345,
                0.09390583634376526,
                0.3768487572669983,
                0.176283597946167,
                0.21614259481430054,
                0.208645299077034,
                0.12746623158454895,
                0.06018827110528946,
                9.5753755569458,
                0.10419425368309021,
                0.08695758134126663,
                0.02623085305094719,
                0.028135841712355614,
                0.03144998103380203,
                0.02533017098903656,
                0.31760460138320923,
                0.013135010376572609,
                0.14931179583072662,
                0.011094588786363602,
                0.43742647767066956,
                0.07984933257102966,
                0.007435825187712908,
                0.0002719605981837958,
                0.19490288197994232,
                0.17254067957401276,
                0.10580078512430191,
                0.595905601978302,
                0.007898650132119656,
                0.07262752205133438,
                0.09769909083843231,
                0.3488623797893524,
                0.13672691583633423,
                0.30900391936302185,
                0.008455222472548485,
                0.019604060798883438,
                0.14417003095149994,
                0.1768692582845688,
                0.13177147507667542,
                0.12490403652191162,
                0.07516885548830032,
                0.1009151041507721,
                0.4281065762042999,
                0.22401945292949677,
                0.07758824527263641,
                0.17131459712982178,
                0.1335124969482422,
                0.12174660712480545,
                0.08760768175125122,
                0.0718325674533844,
                0.20221003890037537,
                0.013274887576699257,
                0.0910269170999527,
                0.34607601165771484,
                0.18842819333076477,
                0.06285962462425232,
                0.0007117378991097212,
                0.15912756323814392,
                0.00832552183419466,
                0.17681114375591278,
                0.09996576607227325,
                0.07866710424423218,
                0.021445980295538902,
                0.0027720557991415262,
                0.16619716584682465,
                0.011192800477147102,
                0.039358604699373245,
                0.14868435263633728,
                0.10052438825368881,
                0.08339264988899231,
                0.04591607302427292,
                0.07272673398256302,
                0.04060199484229088,
                0.32508328557014465,
                0.182909294962883,
                0.8978483080863953,
                0.027242373675107956,
                0.15039072930812836,
                0.7941657304763794,
                0.07535603642463684,
                0.041630666702985764,
                0.0020975384395569563,
                0.2917700409889221
            ]
        }
    }
}