{
    "merging_metrics": {
        "merge_success": 1.0,
        "merge_child_count": 0.0,
        "child_camera_counts": {
            "summary": {
                "min": null,
                "max": null,
                "median": null,
                "mean": null,
                "stddev": null
            },
            "full_data": []
        },
        "child_camera_overlap_with_parent": {
            "summary": {
                "min": null,
                "max": null,
                "median": null,
                "mean": null,
                "stddev": null
            },
            "full_data": []
        },
        "number_images_merged": 236.0,
        "number_cameras_merged": 41.0,
        "number_tracks_merged": 464.0,
        "3d_track_lengths_merged": {
            "summary": {
                "min": 3,
                "max": 27,
                "median": 5.0,
                "mean": 6.4094827586206895,
                "stddev": 4.160103580612732,
                "len": 464,
                "invalid": 0,
                "histogram": {
                    "3": 68,
                    "4": 55,
                    "5": 41,
                    "6": 33,
                    "7": 24,
                    "8": 28,
                    "9": 14,
                    "10": 16,
                    "11": 9,
                    "12": 8,
                    "13": 7,
                    "14": 1,
                    "15": 6,
                    "16": 4,
                    "17": 3,
                    "18": 4,
                    "19": 0,
                    "20": 1,
                    "21": 2,
                    "22": 1,
                    "23": 2,
                    "24": 0,
                    "25": 0,
                    "26": 1
                }
            }
        },
        "reprojection_errors_merged_px": {
            "summary": {
                "min": 0.00013225328667077686,
                "max": 2.942926579036947,
                "median": 0.29186900428799945,
                "mean": 0.37036439291146883,
                "stddev": 0.31059814892113374,
                "len": 2974,
                "invalid": 0,
                "quartiles": {
                    "q0": 0.00013225328667077686,
                    "q1": 0.17477542729980378,
                    "q2": 0.29186900428799945,
                    "q3": 0.4715941014341434,
                    "q4": 2.942926579036947
                }
            }
        },
        "rotation_angle_error_deg": {
            "summary": {
                "min": 0.05218649283051491,
                "max": 3.6380653381347656,
                "median": 0.5573180913925171,
                "mean": 0.8144824504852295,
                "stddev": 0.8009738326072693,
                "len": 41,
                "invalid": 0,
                "quartiles": {
                    "q0": 0.05218649283051491,
                    "q1": 0.2819986045360565,
                    "q2": 0.5573180913925171,
                    "q3": 0.9790392518043518,
                    "q4": 3.6380653381347656
                }
            }
        },
        "translation_error_distance": {
            "summary": {
                "min": 0.010826284065842628,
                "max": 0.8049656748771667,
                "median": 0.15547886490821838,
                "mean": 0.21422851085662842,
                "stddev": 0.18372192978858948,
                "len": 41,
                "invalid": 0,
                "quartiles": {
                    "q0": 0.010826284065842628,
                    "q1": 0.07187838852405548,
                    "q2": 0.15547886490821838,
                    "q3": 0.27941760420799255,
                    "q4": 0.8049656748771667
                }
            }
        },
        "relative_translation_angle_error_deg": {
            "summary": {
                "min": 0.023688163608312607,
                "max": 134.07923889160156,
                "median": 4.028768539428711,
                "mean": 7.350545406341553,
                "stddev": 11.061701774597168,
                "len": 820,
                "invalid": 0,
                "quartiles": {
                    "q0": 0.023688163608312607,
                    "q1": 1.9571931958198547,
                    "q2": 4.028768301010132,
                    "q3": 8.150456666946411,
                    "q4": 134.07923889160156
                }
            }
        },
        "translation_angle_error_deg": {
            "summary": {
                "min": 0.10758915543556213,
                "max": 28.15011978149414,
                "median": 1.1570338010787964,
                "mean": 2.673672676086426,
                "stddev": 4.535794734954834,
                "len": 41,
                "invalid": 0,
                "quartiles": {
                    "q0": 0.10758915543556213,
                    "q1": 0.581535279750824,
                    "q2": 1.1570338010787964,
                    "q3": 2.7908947467803955,
                    "q4": 28.15011978149414
                }
            }
        },
        "relative_rotation_angle_error_deg": {
            "summary": {
                "min": 0.0362955778837204,
                "max": 5.6143975257873535,
                "median": 0.9221687316894531,
                "mean": 1.2646478414535522,
                "stddev": 1.0106440782546997,
                "len": 820,
                "invalid": 0,
                "quartiles": {
                    "q0": 0.0362955778837204,
                    "q1": 0.5597160160541534,
                    "q2": 0.9221687018871307,
                    "q3": 1.6130956709384918,
                    "q4": 5.6143975257873535
                }
            }
        },
        "pose_auc_@1.0_deg": 0.0307,
        "pose_auc_@2.5_deg": 0.1428,
        "pose_auc_@3.0_deg": 0.1799,
        "pose_auc_@5.0_deg": 0.3055,
        "pose_auc_@10.0_deg": 0.511,
        "pose_auc_@20.0_deg": 0.6943,
        "pose_auc_constructed_only_@1.0_deg": 0.0307,
        "pose_auc_constructed_only_@2.5_deg": 0.1428,
        "pose_auc_constructed_only_@3.0_deg": 0.1799,
        "pose_auc_constructed_only_@5.0_deg": 0.3055,
        "pose_auc_constructed_only_@10.0_deg": 0.511,
        "pose_auc_constructed_only_@20.0_deg": 0.6943,
        "focal_length_error_px": {
            "summary": {
                "min": 0.0,
                "max": 1121.942626953125,
                "median": 265.6016540527344,
                "mean": 345.1100158691406,
                "stddev": 245.37840270996094,
                "len": 41,
                "invalid": 0,
                "quartiles": {
                    "q0": 0.0,
                    "q1": 167.41673278808594,
                    "q2": 265.6016540527344,
                    "q3": 477.3238525390625,
                    "q4": 1121.942626953125
                }
            },
            "full_data": [
                477.3238525390625,
                487.1153259277344,
                170.66249084472656,
                611.12646484375,
                43.682212829589844,
                167.41673278808594,
                83.26107788085938,
                219.2722930908203,
                125.70478820800781,
                353.8603210449219,
                1036.5057373046875,
                340.9117126464844,
                429.4136657714844,
                214.8789520263672,
                460.92572021484375,
                65.12147521972656,
                144.27816772460938,
                552.2020263671875,
                192.23951721191406,
                494.89849853515625,
                259.6973571777344,
                167.45118713378906,
                163.47230529785156,
                472.63348388671875,
                465.8765869140625,
                534.3109130859375,
                418.8692321777344,
                548.4757690429688,
                431.806396484375,
                188.2191619873047,
                171.5164337158203,
                0.0,
                555.0383911132812,
                76.6459732055664,
                1121.942626953125,
                409.2821044921875,
                133.7172393798828,
                164.23573303222656,
                192.0520782470703,
                737.8643798828125,
                265.6016540527344
            ]
        },
        "focal_length_error_pct": {
            "summary": {
                "min": 0.0,
                "max": 92.0228500366211,
                "median": 21.447162628173828,
                "mean": 27.933725357055664,
                "stddev": 19.97576332092285,
                "len": 41,
                "invalid": 0,
                "quartiles": {
                    "q0": 0.0,
                    "q1": 13.624408721923828,
                    "q2": 21.447162628173828,
                    "q3": 37.279273986816406,
                    "q4": 92.0228500366211
                }
            },
            "full_data": [
                37.279273986816406,
                38.33139419555664,
                13.648632049560547,
                50.22406768798828,
                3.558342456817627,
                13.624408721923828,
                6.809051036834717,
                17.94959831237793,
                10.23988151550293,
                29.84651756286621,
                84.18663024902344,
                27.906984329223633,
                35.01416015625,
                17.45280647277832,
                37.111572265625,
                5.346590995788574,
                11.752864837646484,
                45.3367805480957,
                15.659784317016602,
                38.98066329956055,
                20.789093017578125,
                13.65388011932373,
                13.187503814697266,
                36.91295623779297,
                36.419368743896484,
                43.3975715637207,
                32.68330383300781,
                44.63507080078125,
                34.90190887451172,
                15.317315101623535,
                13.958043098449707,
                0.0,
                45.56965637207031,
                6.123839378356934,
                92.0228500366211,
                33.63594055175781,
                10.797581672668457,
                13.391694068908691,
                15.53819465637207,
                60.63974380493164,
                21.447162628173828
            ]
        },
        "k1_error": {
            "summary": {
                "min": 0.0,
                "max": 0.060958120971918106,
                "median": 0.011742513626813889,
                "mean": 0.014756049029529095,
                "stddev": 0.014670483767986298,
                "len": 41,
                "invalid": 0,
                "quartiles": {
                    "q0": 0.0,
                    "q1": 0.0032228147611021996,
                    "q2": 0.011742513626813889,
                    "q3": 0.019657984375953674,
                    "q4": 0.060958120971918106
                }
            },
            "full_data": [
                0.0323517806828022,
                0.060958120971918106,
                0.00581976305693388,
                0.020989110693335533,
                0.018406784161925316,
                0.0112813301384449,
                0.019844822585582733,
                0.014007586054503918,
                0.005129951983690262,
                0.023956697434186935,
                0.013559284619987011,
                0.0008966276072897017,
                0.021743491291999817,
                0.01675722934305668,
                0.0013446417870000005,
                0.008403812535107136,
                0.023534508422017097,
                0.0007371487445198,
                0.019657984375953674,
                0.002567018149420619,
                0.05559023842215538,
                0.0016202840488404036,
                0.011742513626813889,
                0.018406353890895844,
                0.007431009318679571,
                0.01431562751531601,
                0.016514698043465614,
                0.010328345000743866,
                0.00808691792190075,
                0.0006996190641075373,
                0.0032228147611021996,
                0.0,
                0.009107253514230251,
                0.00594051880761981,
                0.0017984190490096807,
                0.0,
                0.04324370622634888,
                0.04724647477269173,
                0.0,
                0.012174655683338642,
                0.015580853447318077
            ]
        },
        "k2_error": {
            "summary": {
                "min": 0.0,
                "max": 0.07144887000322342,
                "median": 0.001685850671492517,
                "mean": 0.0064752111211419106,
                "stddev": 0.013667917810380459,
                "len": 41,
                "invalid": 0,
                "quartiles": {
                    "q0": 0.0,
                    "q1": 0.00047706408076919615,
                    "q2": 0.001685850671492517,
                    "q3": 0.005084425676614046,
                    "q4": 0.07144887000322342
                }
            },
            "full_data": [
                0.017910713329911232,
                0.07144887000322342,
                0.001176243182271719,
                0.005084425676614046,
                0.002852735808119178,
                0.0004763816250488162,
                0.0019206551369279623,
                0.001446147682145238,
                0.0005228453665040433,
                0.007468734867870808,
                0.00013758521527051926,
                9.735559615364764e-06,
                0.001685850671492517,
                0.0029684146866202354,
                0.010055385529994965,
                0.006140400189906359,
                0.002074439311400056,
                5.915636938880198e-05,
                0.0012571559054777026,
                0.0004886783426627517,
                0.007464555557817221,
                0.0012542521581053734,
                0.0017700010212138295,
                0.0025098402984440327,
                0.0008957451791502535,
                0.005251881666481495,
                0.005015404429286718,
                0.001631258986890316,
                0.0033664084039628506,
                0.019776910543441772,
                0.00016455865988973528,
                0.0,
                0.0009754126658663154,
                2.1490996005013585e-05,
                5.21113324793987e-05,
                0.0,
                0.002318986924365163,
                0.029326744377613068,
                0.0,
                0.00047706408076919615,
                0.04802645370364189
            ]
        }
    }
}